iverilog/signExtend.v
module signExtend(
	input wire[24:0] entrada,
	output wire[31:0] saida
);

//extende o sinal replicando o ultimo bit
assign saida = {{7{entrada[24]}}, entrada[24:0]};

endmodule

Controle.v
module Controle(
	input wire [2:0] OpCode,
	output reg MemtoReg, MemEn, MemOp, FonteEscrita, RegEsc, Stop, Clear,
	output reg [3:0] ALUCode
);

//O codigo é basicamente um decodificador que gera os sinais de 
//controle a partir do opcode
always @(*)
begin
	//operacao de soma
	if(OpCode == 3'b000)
	begin
		MemtoReg = 1'b0;
		MemEn = 1'b0;
		MemOp = 1'b0;
		FonteEscrita = 1'b0;
		RegEsc = 1'b1;
		ALUCode = 4'b1000;
		Stop = 1'b0;
		Clear = 1'b0;
	end
	//operacao de subtracao
	else if(OpCode == 3'b001)
	begin
		MemtoReg = 1'b0;
		MemEn = 1'b0;
		MemOp = 1'b0;
		FonteEscrita = 1'b0;
		RegEsc = 1'b1;
		ALUCode = 4'b0100;
		Stop = 1'b0;
		Clear = 1'b0;
	end
	//operacao de divisao
	else if(OpCode == 3'b010)
	begin
		MemtoReg = 1'b0;
		MemEn = 1'b0;
		MemOp = 1'b0;
		FonteEscrita = 1'b0;
		RegEsc = 1'b1;
		ALUCode = 4'b0001;
		Stop = 1'b0;
		Clear = 1'b0;
	end
	//operacao de multiplicacao
	else if(OpCode == 3'b011)
	begin
		MemtoReg = 1'b0;
		MemEn = 1'b0;
		MemOp = 1'b0;
		FonteEscrita = 1'b0;
		RegEsc = 1'b1;
		ALUCode = 4'b0010;
		Stop = 1'b0;
		Clear = 1'b0;
	end
	//operacao de memory clear
	else if(OpCode == 3'b100)
	begin
		MemtoReg = 1'b0;
		MemEn = 1'b1;
		MemOp = 1'b0;
		FonteEscrita = 1'b0;
		RegEsc = 1'b0;
		ALUCode = 4'b0001;
		Stop = 1'b0;
		Clear = 1'b1;
	end
	//operacao de memory read
	else if(OpCode == 3'b110)
	begin
		MemtoReg = 1'b1;
		MemEn = 1'b1;
		MemOp = 1'b0;
		FonteEscrita = 1'b1;
		RegEsc = 1'b1;
		ALUCode = 4'b0001;
		Stop = 1'b0;
		Clear = 1'b0;
	end
	//operacao de memory write
	else if(OpCode == 3'b111)
	begin
		MemtoReg = 1'b0;
		MemEn = 1'b1;
		MemOp = 1'b1;
		FonteEscrita = 1'b0;
		RegEsc = 1'b0;
		ALUCode = 4'b0001;
		Stop = 1'b0;
		Clear = 1'b0;
	end
	//operacao de parada
	else
	begin
		MemtoReg = 1'b0;
		MemEn = 1'b0;
		MemOp = 1'b0;
		FonteEscrita = 1'b0;
		RegEsc = 1'b0;
		ALUCode = 4'b0001;
		Stop = 1'b1;
		Clear = 1'b0;
	end
end
endmodule

iverilog/Mem.v
module Mem(
	input wire [31:0] ReadPC, RWAddr, Value,
	input wire OP2En, OP2RW, Clk, Clear,
	output reg [31:0] Instr, Data
);

//declara a memoria
reg [31:0] memory [1023:0];

//carrega os dados da memoria
initial
begin
$readmemh("memoria.txt", memory);
end

//para limpar a memoria
integer i;

//sempre numa borda de subida de clock
always @(posedge Clk)
begin
	//if(OP2En == 1'b1)
	//begin
		Data = memory[RWAddr];
	//end
end

always @(posedge !Clk)
begin
	//instrucao sempre lida
	Instr = memory[ReadPC];
	//se o clear estiver desativado
	if(Clear == 1'b0)
	begin
		if((OP2En == 1'b1) & (OP2RW == 1'b1))
		begin
			memory[RWAddr] = Value;
		end
	end
	//limpa a memoria na posicao indicada	
	else if(Clear == 1'b1)
	begin
		memory[RWAddr] = 32'h00000000;
	end
end

endmodule

RegisterFile.v
module RegisterFile(
	input wire [1:0] RegEsc, Fonte1, Fonte2,
	input wire Esc, Clk,
	input wire [31:0] Dado,
	output reg [31:0] Dado1, Dado2,
	output wire	[31:0] RA, RB, RACC
);

//declara e assimila os tres registradores
reg [31:0] RegA, RegB, Acc;
assign	RA = RegA;
assign	RB = RegB;
assign	RACC = Acc;


//realiza a gravacao na descida de clock
always @(negedge Clk)
begin
	if (Esc == 1'b1)
	begin
		case(RegEsc)
			2'b00: RegA = Dado;
			2'b01: RegB = Dado;
			default: Acc = Dado;
		endcase
	end
end

//realiza as leituras na subida de clock
always @(posedge Clk)
begin
	//if (Esc == 1'b0)
	//begin
		case(Fonte1)
			2'b00: Dado1 = RegA;
			2'b01: Dado1 = RegB;
			2'b10: Dado1 = Acc;
			default: Dado1 = 32'b0;
		endcase
		case(Fonte2)
			2'b00: Dado2 = RegA;
			2'b01: Dado2 = RegB;
			2'b10: Dado2 = Acc;
			default: Dado2 = 32'b0;
		endcase
	//end
end
endmodule

ALU.v
module ALU (
	input wire [31:0] input1, input2,
	input wire [3:0] op,
	output reg [31:0] output1
);

//reg [31:0] result;
always @(*)
begin
	case(op)
		4'b1000: output1 =  input1 + input2;
		4'b0100: output1 =  input1 - input2;
		4'b0010: output1 =  input1 * input2;
		4'b0001: output1 =  input1 / input2;
		default: output1 = input1;
	endcase
	//output1 <= result;
end
endmodule

iverilog/CALC1.v
module CALC1 (
input wire Clk,
output wire [31:0] RegA, RegB, RAcc, InstrAtual
);

//arquivo com o caminho de dados:

//sinais internos
reg [1:0] FonteA, Dest, DestEscrita, Acc;
reg [31:0] DadosEscrita, PC, PCP;
wire [31:0] DadosA, DadosB, ResultALU, imediato;
wire [31:0] MemData, instrucao;
wire RegEsc, MemEn, MemOp, Clear;
wire FonteEscrita, MemtoReg, Stop;
wire [3:0] opALU;

//inicializa o pc com 0
initial PC = 32'h00000000;
assign InstrAtual = instrucao;

//instancia a alu
ALU instALU(
	.input1(DadosA),
	.input2(imediato),
	.op(opALU),
	.output1(ResultALU)
);

//instancia o banco de registradores
RegisterFile insRegisterFile(
	.RegEsc(DestEscrita),
	.Fonte1(FonteA),
	.Fonte2(FonteA),
	.Esc(RegEsc),
	.Clk(Clk),
	.Dado(DadosEscrita),
	.Dado1(DadosA),
	.Dado2(DadosB),
	.RA(RegA),
	.RB(RegB),
	.RACC(RAcc)
);

//instancia a memoria
Mem instMem(
	.ReadPC(PC),
	.RWAddr(imediato),
	.Value(DadosB),
	.OP2En(MemEn),
	.OP2RW(MemOp),
	.Clk(Clk),
	.Instr(instrucao),
	.Data(MemData),
	.Clear(Clear)
);

//instancia o controle
Controle instControle(
	.OpCode(instrucao[31:29]),
	.MemtoReg(MemtoReg),
	.MemEn(MemEn),
	.MemOp(MemOp),
	.FonteEscrita(FonteEscrita),
	.RegEsc(RegEsc),
	.ALUCode(opALU),
	.Stop(Stop),
	.Clear(Clear)
);

//instancia o extensor de sinal
signExtend instSignExtend(
	.entrada(instrucao[24:0]),
	.saida(imediato)
);

always @(*)
begin
	//assimila sinais internos
	Dest = instrucao[26:25];
	FonteA = instrucao[28:27];
	Acc = 2'b10;
	PCP = PC + 1;
	//define a registrador de escrita no banco de registradores
	if(FonteEscrita == 1'b0)
		DestEscrita = Acc;
	else
		DestEscrita = Dest;
	//define o que vai ser escrito no banco de registradores
	if(MemtoReg == 1'b0)
		DadosEscrita = ResultALU;
	else
		DadosEscrita = MemData;
end

//analisa se o PC vai ser atualizado ou não
always @(posedge Clk)
begin
	if(Stop == 1'b0)
		PC = PCP;
end
endmodule

iverilog/tb_CALC1.v
module tb_CALC1();

reg clk = 0;
wire [31:0] regA, regB, rAcc, Instrucao;

CALC1 instCalc (
	.Clk(clk),
	.RegA(regA),
	.RegB(regB),
	.RAcc(rAcc),
	.InstrAtual(Instrucao)
);

always #10 clk = !clk;

initial
begin
$dumpfile("saida.vcd");
$dumpvars;
$monitor("No tempo %t, RegA = %h, RegB = %h, RAcc = %h, Instrucao = %h",$time, regA, regB, rAcc, Instrucao);
#250
$finish;
end

endmodule

iverilog/saida.vcd
$date
	Sun Jun 23 16:18:18 2019
$end
$version
	Icarus Verilog
$end
$timescale
	1s
$end
$scope module tb_CALC1 $end
$var wire 32 ! regB [31:0] $end
$var wire 32 " regA [31:0] $end
$var wire 32 # rAcc [31:0] $end
$var wire 32 $ Instrucao [31:0] $end
$var reg 1 % clk $end
$scope module instCalc $end
$var wire 1 % Clk $end
$var wire 32 & InstrAtual [31:0] $end
$var wire 4 ' opALU [3:0] $end
$var wire 32 ( instrucao [31:0] $end
$var wire 32 ) imediato [31:0] $end
$var wire 1 * Stop $end
$var wire 32 + ResultALU [31:0] $end
$var wire 1 , RegEsc $end
$var wire 32 - RegB [31:0] $end
$var wire 32 . RegA [31:0] $end
$var wire 32 / RAcc [31:0] $end
$var wire 1 0 MemtoReg $end
$var wire 1 1 MemOp $end
$var wire 1 2 MemEn $end
$var wire 32 3 MemData [31:0] $end
$var wire 1 4 FonteEscrita $end
$var wire 32 5 DadosB [31:0] $end
$var wire 32 6 DadosA [31:0] $end
$var wire 1 7 Clear $end
$var reg 2 8 Acc [1:0] $end
$var reg 32 9 DadosEscrita [31:0] $end
$var reg 2 : Dest [1:0] $end
$var reg 2 ; DestEscrita [1:0] $end
$var reg 2 < FonteA [1:0] $end
$var reg 32 = PC [31:0] $end
$var reg 32 > PCP [31:0] $end
$scope module insRegisterFile $end
$var wire 1 % Clk $end
$var wire 32 ? Dado [31:0] $end
$var wire 2 @ Fonte1 [1:0] $end
$var wire 2 A Fonte2 [1:0] $end
$var wire 32 B RA [31:0] $end
$var wire 32 C RACC [31:0] $end
$var wire 32 D RB [31:0] $end
$var wire 2 E RegEsc [1:0] $end
$var wire 1 , Esc $end
$var reg 32 F Acc [31:0] $end
$var reg 32 G Dado1 [31:0] $end
$var reg 32 H Dado2 [31:0] $end
$var reg 32 I RegA [31:0] $end
$var reg 32 J RegB [31:0] $end
$upscope $end
$scope module instALU $end
$var wire 32 K input1 [31:0] $end
$var wire 4 L op [3:0] $end
$var wire 32 M input2 [31:0] $end
$var reg 32 N output1 [31:0] $end
$upscope $end
$scope module instControle $end
$var wire 3 O OpCode [2:0] $end
$var reg 4 P ALUCode [3:0] $end
$var reg 1 7 Clear $end
$var reg 1 4 FonteEscrita $end
$var reg 1 2 MemEn $end
$var reg 1 1 MemOp $end
$var reg 1 0 MemtoReg $end
$var reg 1 , RegEsc $end
$var reg 1 * Stop $end
$upscope $end
$scope module instMem $end
$var wire 1 7 Clear $end
$var wire 1 % Clk $end
$var wire 1 2 OP2En $end
$var wire 1 1 OP2RW $end
$var wire 32 Q ReadPC [31:0] $end
$var wire 32 R Value [31:0] $end
$var wire 32 S RWAddr [31:0] $end
$var reg 32 T Data [31:0] $end
$var reg 32 U Instr [31:0] $end
$upscope $end
$scope module instSignExtend $end
$var wire 25 V entrada [24:0] $end
$var wire 32 W saida [31:0] $end
$upscope $end
$upscope $end
$upscope $end
$enddefinitions $end
#0
$dumpvars
b10011 W
b10011 V
b11000000000000000000000000010011 U
bx T
b10011 S
bx R
b0 Q
b1 P
b110 O
bx N
b10011 M
b1 L
bx K
bx J
bx I
bx H
bx G
bx F
b0 E
bx D
bx C
bx B
b0 A
b0 @
bx ?
b1 >
b0 =
b0 <
b0 ;
b0 :
bx 9
b10 8
07
bx 6
bx 5
14
bx 3
12
01
10
bx /
bx .
bx -
1,
bx +
0*
b10011 )
b11000000000000000000000000010011 (
b1 '
b11000000000000000000000000010011 &
0%
b11000000000000000000000000010011 $
bx #
bx "
bx !
$end
#10
b101 9
b101 ?
b10 >
b101 3
b101 T
b1 =
b1 Q
1%
#20
bx 9
bx ?
b10 ;
b10 E
b100 '
b100 L
b100 P
04
02
00
b1 )
b1 M
b1 S
b1 W
b1 V
b1 O
b101 "
b101 .
b101 B
b101 I
b100000000000000000000000000001 $
b100000000000000000000000000001 &
b100000000000000000000000000001 (
b100000000000000000000000000001 U
0%
#30
b100 9
b100 ?
b11 >
b100 +
b100 N
b10 =
b10 Q
b100000000000000000000000000001 3
b100000000000000000000000000001 T
b101 5
b101 H
b101 R
b101 6
b101 G
b101 K
1%
#40
b10 9
b10 ?
b10 +
b10 N
b1 '
b1 L
b1 P
b10 )
b10 M
b10 S
b10 W
b10 V
b10 O
b10 <
b10 @
b10 A
b100 #
b100 /
b100 C
b100 F
b1010000000000000000000000000010 $
b1010000000000000000000000000010 &
b1010000000000000000000000000010 (
b1010000000000000000000000000010 U
0%
#50
b100 >
b100 5
b100 H
b100 R
b100 6
b100 G
b100 K
b1010000000000000000000000000010 3
b1010000000000000000000000000010 T
b11 =
b11 Q
1%
#60
b10100 9
b10100 ?
b10100 +
b10100 N
b10 '
b10 L
b10 P
b101 )
b101 M
b101 S
b101 W
b101 V
b11 O
b10 #
b10 /
b10 C
b10 F
b1110000000000000000000000000101 $
b1110000000000000000000000000101 &
b1110000000000000000000000000101 (
b1110000000000000000000000000101 U
0%
#70
b1010 9
b1010 ?
b101 >
b1010 +
b1010 N
b100 =
b100 Q
b11110000000000000000000000010100 3
b11110000000000000000000000010100 T
b10 5
b10 H
b10 R
b10 6
b10 G
b10 K
1%
#80
b1100 9
b1100 ?
b1100 +
b1100 N
b1000 '
b1000 L
b1000 P
b1010 )
b1010 M
b1010 S
b1010 W
b1010 V
b0 O
b1010 #
b1010 /
b1010 C
b1010 F
b10000000000000000000000001010 $
b10000000000000000000000001010 &
b10000000000000000000000001010 (
b10000000000000000000000001010 U
0%
#90
b10100 9
b10100 ?
b10100 +
b10100 N
b110 >
b1010 5
b1010 H
b1010 R
b1010 6
b1010 G
b1010 K
b10100000000000000000000000000000 3
b10100000000000000000000000000000 T
b101 =
b101 Q
1%
#100
b0 9
b0 ?
b0 +
b0 N
b1 '
b1 L
b1 P
0,
11
12
b10100 )
b10100 M
b10100 S
b10100 W
b10100 V
b111 O
b10100 #
b10100 /
b10100 C
b10100 F
b11110000000000000000000000010100 $
b11110000000000000000000000010100 &
b11110000000000000000000000010100 (
b11110000000000000000000000010100 U
0%
#110
b1 9
b1 ?
b111 >
b1 +
b1 N
b110 =
b110 Q
b0 3
b0 T
b10100 5
b10100 H
b10100 R
b10100 6
b10100 G
b10100 K
1%
#120
b0 9
b0 ?
b1 ;
b1 E
1,
14
01
10
b110 O
b0 <
b0 @
b0 A
b1 :
b11000010000000000000000000010100 $
b11000010000000000000000000010100 &
b11000010000000000000000000010100 (
b11000010000000000000000000010100 U
0%
#130
b0 +
b0 N
b10100 9
b10100 ?
b1000 >
b101 5
b101 H
b101 R
b101 6
b101 G
b101 K
b10100 3
b10100 T
b111 =
b111 Q
1%
#140
17
0,
04
b100 O
b10 ;
b10 E
b0 :
b10100 !
b10100 -
b10100 D
b10100 J
b10000000000000000000000000010100 $
b10000000000000000000000000010100 &
b10000000000000000000000000010100 (
b10000000000000000000000000010100 U
0%
#150
b1001 >
b1000 =
b1000 Q
1%
#160
b101 9
b101 ?
b101 +
b101 N
07
b1000 '
b1000 L
b1000 P
1,
02
00
b0 )
b0 M
b0 S
b0 W
b0 V
b0 O
b11 <
b11 @
b11 A
b11000000000000000000000000000 $
b11000000000000000000000000000 &
b11000000000000000000000000000 (
b11000000000000000000000000000 U
0%
#170
b0 9
b0 ?
b0 +
b0 N
b1010 >
b0 5
b0 H
b0 R
b0 6
b0 G
b0 K
b11000000000000000000000000010011 3
b11000000000000000000000000010011 T
b1001 =
b1001 Q
1%
#180
b11000000000000000000000000010011 9
b11000000000000000000000000010011 ?
b0 ;
b0 E
b1 '
b1 L
b1 P
14
12
10
b10100 )
b10100 M
b10100 S
b10100 W
b10100 V
b110 O
b0 <
b0 @
b0 A
b0 #
b0 /
b0 C
b0 F
b11000000000000000000000000010100 $
b11000000000000000000000000010100 &
b11000000000000000000000000010100 (
b11000000000000000000000000010100 U
0%
#190
b0 9
b0 ?
b1011 >
b1010 =
b1010 Q
b0 3
b0 T
b101 5
b101 H
b101 R
b101 6
b101 G
b101 K
1%
#200
bx 9
bx ?
b10 ;
b10 E
bx +
bx N
1*
0,
04
02
00
b0 )
b0 M
b0 S
b0 W
b0 V
b101 O
b0 "
b0 .
b0 B
b0 I
b10100000000000000000000000000000 $
b10100000000000000000000000000000 &
b10100000000000000000000000000000 (
b10100000000000000000000000000000 U
0%
#210
b0 5
b0 H
b0 R
b0 6
b0 G
b0 K
b11000000000000000000000000010011 3
b11000000000000000000000000010011 T
1%
